pyutils/__init__.py
pyutils/pyutils.py
pyutils2/__init__.py
pyutils2/pyutils.py
pyutils2-0.0.2.dist-info/LICENSE
pyutils2-0.0.2.dist-info/METADATA
pyutils2-0.0.2.dist-info/WHEEL
pyutils2-0.0.2.dist-info/top_level.txt
pyutils2-0.0.2.dist-info/RECORD
