Metadata-Version: 2.1
Name: pyutils2
Version: 0.0.2
Summary: python custom utils
Home-page: https://github.com/xindzju
Author: Xin Deng
Author-email: xindeng3@gmail.com
License: UNKNOWN
Platform: UNKNOWN
Classifier: Programming Language :: Python :: 3
Classifier: License :: OSI Approved :: MIT License
Classifier: Operating System :: OS Independent
